{
  "testId" : "1-addstudent.gspec",
  "name" : "addStudent.gspec",
  "report" : {
    "nodes" : [ {
      "name" : "Simple check",
      "status" : "info",
      "nodes" : [ {
        "name" : "check  addStudent.gspec --url http://localhost/addStudent.html --size 1024x768 --htmlreport izvjestaji",
        "status" : "info",
        "nodes" : [ {
          "name" : "Check layout: addStudent.gspec included tags: ",
          "status" : "info",
          "time" : 1541290122645,
          "sections" : [ ],
          "objects" : { },
          "screenshot" : "layout-1-screenshot.png",
          "type" : "layout"
        } ],
        "time" : 1541290121802,
        "type" : "node"
      } ],
      "time" : 1541290113876,
      "type" : "node"
    } ]
  }
}